[{"id":"38x3443486","equip_model":"BH60M","equipment_sl_no":"BH60M-60355","equi_desc":"BEML-BH60M-REAR DUMPER","equip_category":"S","equip_war_terms":"C&M EQPT - 1 Year Std Warranty","eq_last_hmr":"19186","eq_last_km_run":"0","functional_loc":"1304-SCCLT-MHR-RGM2","functional_loc_idofreference":"45x1642527","functional_loc_Label":"1304-SCCLT-MHR-RGM2","account_id":"SCCL RAMAGUNDAM","account_id_idofreference":"11x1632294","account_id_Label":"SCCL RAMAGUNDAM","eq_run_war_st":"Outside Warranty","equipmentid":"3443486","starred":""},{"id":"38x1649934","equip_model":"BL200-1","equipment_sl_no":"BL200-1-10181","equi_desc":"BL200-1 WHEEL LOADER","equip_category":"S","equip_war_terms":"C&M EQPT  - 1 YEAR OR 4000 HRS","eq_last_hmr":"2978","eq_last_km_run":"0","functional_loc":"1304-SCCLT-MHR-RGM2","functional_loc_idofreference":"45x1642527","functional_loc_Label":"1304-SCCLT-MHR-RGM2","account_id":"SCCL, SRIRAMPUR","account_id_idofreference":"11x1634658","account_id_Label":"SCCL, SRIRAMPUR","eq_run_war_st":"Outside Warranty","equipmentid":"1649934","starred":""},{"id":"38x1649889","equip_model":"BL200-1","equipment_sl_no":"BL200-1-10179","equi_desc":"BL200-1 WHEEL LOADER","equip_category":"S","equip_war_terms":"C&M EQPT  - 1 YEAR OR 4000 HRS","eq_last_hmr":"3584","eq_last_km_run":"0","functional_loc":"1304-SCCLT-MHR-RGM2","functional_loc_idofreference":"45x1642527","functional_loc_Label":"1304-SCCLT-MHR-RGM2","account_id":"SCCL, SRIRAMPUR","account_id_idofreference":"11x1634658","account_id_Label":"SCCL, SRIRAMPUR","eq_run_war_st":"Outside Warranty","equipmentid":"1649889","starred":""},{"id":"38x1649867","equip_model":"BL200-1","equipment_sl_no":"BL200-1-10178","equi_desc":"BL200-1 WHEEL LOADER","equip_category":"S","equip_war_terms":"C&M EQPT  - 1 YEAR OR 4000 HRS","eq_last_hmr":"5476","eq_last_km_run":"0","functional_loc":"1304-SCCLT-MHR-RGM2","functional_loc_idofreference":"45x1642527","functional_loc_Label":"1304-SCCLT-MHR-RGM2","account_id":"SCCL, SRIRAMPUR","account_id_idofreference":"11x1634658","account_id_Label":"SCCL, SRIRAMPUR","eq_run_war_st":"Outside Warranty","equipmentid":"1649867","starred":""},{"id":"38x1649488","equip_model":"BL200-1","equipment_sl_no":"BL200-1-10160","equi_desc":"BL200-1 WHEEL LOADER","equip_category":"S","equip_war_terms":"C&M EQPT  - 1 YEAR OR 4000 HRS","eq_last_hmr":"4694","eq_last_km_run":"0","functional_loc":"1304-SCCLT-MHR-RGM2","functional_loc_idofreference":"45x1642527","functional_loc_Label":"1304-SCCLT-MHR-RGM2","account_id":"SCCL, SRIRAMPUR","account_id_idofreference":"11x1634658","account_id_Label":"SCCL, SRIRAMPUR","eq_run_war_st":"Outside Warranty","equipmentid":"1649488","starred":""},{"id":"38x3479788","equip_model":"BL14TH","equipment_sl_no":"BL14TH-18098","equi_desc":"BL14TH TYRE HANDLER","equip_category":"S","equip_war_terms":"C&M EQPT - 12 MONTHS OR 3000 HRS","eq_last_hmr":"889","eq_last_km_run":"0","functional_loc":"1304-SCCLT-MHR-RGM2","functional_loc_idofreference":"45x1642527","functional_loc_Label":"1304-SCCLT-MHR-RGM2","account_id":"SCCL GODAVARIKHANI","account_id_idofreference":"11x1632287","account_id_Label":"SCCL GODAVARIKHANI","eq_run_war_st":"Outside Warranty","equipmentid":"3479788","starred":""},{"id":"38x3479769","equip_model":"BL14TH","equipment_sl_no":"BL14TH-18097","equi_desc":"BL14TH TYRE HANDLER","equip_category":"S","equip_war_terms":"C&M EQPT - 3000 Hrs OR 1 Year","eq_last_hmr":"250","eq_last_km_run":"0","functional_loc":"1304-SCCLT-MHR-RGM2","functional_loc_idofreference":"45x1642527","functional_loc_Label":"1304-SCCLT-MHR-RGM2","account_id":"SCCL, SRIRAMPUR","account_id_idofreference":"11x1634658","account_id_Label":"SCCL, SRIRAMPUR","eq_run_war_st":"Outside Warranty","equipmentid":"3479769","starred":""},{"id":"38x3454739","equip_model":"BH60M","equipment_sl_no":"BH60M-60635","equi_desc":"REAR DUMPER","equip_category":"S","equip_war_terms":"C&M EQPT - 1 Year Std Warranty","eq_last_hmr":"2999","eq_last_km_run":"0","functional_loc":"1304-SCCLT-MHR-RGM2","functional_loc_idofreference":"45x1642527","functional_loc_Label":"1304-SCCLT-MHR-RGM2","account_id":"SCCL RAMAGUNDAM","account_id_idofreference":"11x1632294","account_id_Label":"SCCL RAMAGUNDAM","eq_run_war_st":"Outside Warranty","equipmentid":"3454739","starred":""},{"id":"38x3454726","equip_model":"BH60M","equipment_sl_no":"BH60M-60632","equi_desc":"REAR DUMPER","equip_category":"S","equip_war_terms":"C&M EQPT - 1 Year Std Warranty","eq_last_hmr":"7648","eq_last_km_run":"0","functional_loc":"1304-SCCLT-MHR-RGM2","functional_loc_idofreference":"45x1642527","functional_loc_Label":"1304-SCCLT-MHR-RGM2","account_id":"SCCL RAMAGUNDAM","account_id_idofreference":"11x1632294","account_id_Label":"SCCL RAMAGUNDAM","eq_run_war_st":"Outside Warranty","equipmentid":"3454726","starred":""},{"id":"38x3454343","equip_model":"BH60M","equipment_sl_no":"BH60M-60621","equi_desc":"REAR DUMPER","equip_category":"S","equip_war_terms":"C&M EQPT - 1 Year Std Warranty","eq_last_hmr":"2267","eq_last_km_run":"0","functional_loc":"1304-SCCLT-MHR-RGM2","functional_loc_idofreference":"45x1642527","functional_loc_Label":"1304-SCCLT-MHR-RGM2","account_id":"SCCL RAMAGUNDAM","account_id_idofreference":"11x1632294","account_id_Label":"SCCL RAMAGUNDAM","eq_run_war_st":"Outside Warranty","equipmentid":"3454343","starred":""},{"id":"38x3454339","equip_model":"BH60M","equipment_sl_no":"BH60M-60620","equi_desc":"REAR DUMPER","equip_category":"S","equip_war_terms":"C&M EQPT - 1 Year Std Warranty","eq_last_hmr":"2750","eq_last_km_run":"0","functional_loc":"1304-SCCLT-MHR-RGM2","functional_loc_idofreference":"45x1642527","functional_loc_Label":"1304-SCCLT-MHR-RGM2","account_id":"SCCL RAMAGUNDAM","account_id_idofreference":"11x1632294","account_id_Label":"SCCL RAMAGUNDAM","eq_run_war_st":"Outside Warranty","equipmentid":"3454339","starred":""},{"id":"38x3454297","equip_model":"BH60M","equipment_sl_no":"BH60M-60619","equi_desc":"REAR DUMPER","equip_category":"S","equip_war_terms":"C&M EQPT - 1 Year Std Warranty","eq_last_hmr":"16848","eq_last_km_run":"0","functional_loc":"1304-SCCLT-MHR-RGM2","functional_loc_idofreference":"45x1642527","functional_loc_Label":"1304-SCCLT-MHR-RGM2","account_id":"SCCL RAMAGUNDAM","account_id_idofreference":"11x1632294","account_id_Label":"SCCL RAMAGUNDAM","eq_run_war_st":"Outside Warranty","equipmentid":"3454297","starred":""},{"id":"38x3453769","equip_model":"BH60M","equipment_sl_no":"BH60M-60607","equi_desc":"REAR DUMPER","equip_category":"S","equip_war_terms":"C&M EQPT - 1 Year Std Warranty","eq_last_hmr":"2693","eq_last_km_run":"0","functional_loc":"1304-SCCLT-MHR-RGM2","functional_loc_idofreference":"45x1642527","functional_loc_Label":"1304-SCCLT-MHR-RGM2","account_id":"SCCL RAMAGUNDAM","account_id_idofreference":"11x1632294","account_id_Label":"SCCL RAMAGUNDAM","eq_run_war_st":"Outside Warranty","equipmentid":"3453769","starred":""},{"id":"38x3453728","equip_model":"BH60M","equipment_sl_no":"BH60M-60606","equi_desc":"REAR DUMPER","equip_category":"S","equip_war_terms":"C&M EQPT - 1 Year Std Warranty","eq_last_hmr":"2986","eq_last_km_run":"0","functional_loc":"1304-SCCLT-MHR-RGM2","functional_loc_idofreference":"45x1642527","functional_loc_Label":"1304-SCCLT-MHR-RGM2","account_id":"SCCL RAMAGUNDAM","account_id_idofreference":"11x1632294","account_id_Label":"SCCL RAMAGUNDAM","eq_run_war_st":"Outside Warranty","equipmentid":"3453728","starred":""},{"id":"38x3443660","equip_model":"BH60M","equipment_sl_no":"BH60M-60359","equi_desc":"BEML-BH60M-REAR DUMPER","equip_category":"S","equip_war_terms":"C&M EQPT - 1 Year Std Warranty","eq_last_hmr":"78","eq_last_km_run":"0","functional_loc":"1304-SCCLT-MHR-RGM2","functional_loc_idofreference":"45x1642527","functional_loc_Label":"1304-SCCLT-MHR-RGM2","account_id":"SCCL RAMAGUNDAM","account_id_idofreference":"11x1632294","account_id_Label":"SCCL RAMAGUNDAM","eq_run_war_st":"Outside Warranty","equipmentid":"3443660","starred":""},{"id":"38x3441342","equip_model":"BH60M","equipment_sl_no":"BH60M-60305","equi_desc":"BEML-BH60M-REAR DUMPER","equip_category":"S","equip_war_terms":"C&M EQPT - 1 Year Std Warranty","eq_last_hmr":"16080","eq_last_km_run":"0","functional_loc":"1304-SCCLT-MHR-RGM2","functional_loc_idofreference":"45x1642527","functional_loc_Label":"1304-SCCLT-MHR-RGM2","account_id":"SCCL RAMAGUNDAM","account_id_idofreference":"11x1632294","account_id_Label":"SCCL RAMAGUNDAM","eq_run_war_st":"Outside Warranty","equipmentid":"3441342","starred":""},{"id":"38x3441296","equip_model":"BH60M","equipment_sl_no":"BH60M-60304","equi_desc":"BEML-BH60M-REAR DUMPER","equip_category":"S","equip_war_terms":"C&M EQPT - 1 Year Std Warranty","eq_last_hmr":"18085","eq_last_km_run":"0","functional_loc":"1304-SCCLT-MHR-RGM2","functional_loc_idofreference":"45x1642527","functional_loc_Label":"1304-SCCLT-MHR-RGM2","account_id":"SCCL RAMAGUNDAM","account_id_idofreference":"11x1632294","account_id_Label":"SCCL RAMAGUNDAM","eq_run_war_st":"Outside Warranty","equipmentid":"3441296","starred":""},{"id":"38x1723759","equip_model":"WS28","equipment_sl_no":"WS28-205","equi_desc":"WS28-WATER SPRINKLER","equip_category":"S","equip_war_terms":"C&M EQPT - 3000 Hrs OR 1 Year","eq_last_hmr":"1900","eq_last_km_run":"0","functional_loc":"1304-SCCLT-MHR-RGM2","functional_loc_idofreference":"45x1642527","functional_loc_Label":"1304-SCCLT-MHR-RGM2","account_id":"SCCL RAMAGUNDAM","account_id_idofreference":"11x1632294","account_id_Label":"SCCL RAMAGUNDAM","eq_run_war_st":"Outside Warranty","equipmentid":"1723759","starred":""},{"id":"38x1723756","equip_model":"WS28","equipment_sl_no":"WS28-204","equi_desc":"WS28-WATER SPRINKLER","equip_category":"S","equip_war_terms":"C&M EQPT - 3000 Hrs OR 1 Year","eq_last_hmr":"4423","eq_last_km_run":"0","functional_loc":"1304-SCCLT-MHR-RGM2","functional_loc_idofreference":"45x1642527","functional_loc_Label":"1304-SCCLT-MHR-RGM2","account_id":"SCCL RAMAGUNDAM","account_id_idofreference":"11x1632294","account_id_Label":"SCCL RAMAGUNDAM","eq_run_war_st":"Outside Warranty","equipmentid":"1723756","starred":""},{"id":"38x1718982","equip_model":"WS28-2","equipment_sl_no":"WS28-2-344","equi_desc":"WS28-2 WATER SPRINKLER","equip_category":"S","equip_war_terms":"C&M EQPT - 3000 Hrs OR 1 Year","eq_last_hmr":"4503","eq_last_km_run":"0","functional_loc":"1304-SCCLT-MHR-RGM2","functional_loc_idofreference":"45x1642527","functional_loc_Label":"1304-SCCLT-MHR-RGM2","account_id":"SCCL RAMAGUNDAM","account_id_idofreference":"11x1632294","account_id_Label":"SCCL RAMAGUNDAM","eq_run_war_st":"Outside Warranty","equipmentid":"1718982","starred":""},{"id":"38x1710005","equip_model":"WS28-2","equipment_sl_no":"WS28-2-28159","equi_desc":"WATER SPLINKER","equip_category":"S","equip_war_terms":"C&M EQPT - 3000 Hrs OR 1 Year","eq_last_hmr":"1","eq_last_km_run":"0","functional_loc":"1304-SCCLT-MHR-RGM2","functional_loc_idofreference":"45x1642527","functional_loc_Label":"1304-SCCLT-MHR-RGM2","account_id":"SCCL RAMAGUNDAM","account_id_idofreference":"11x1632294","account_id_Label":"SCCL RAMAGUNDAM","eq_run_war_st":"Outside Warranty","equipmentid":"1710005","starred":""},{"id":"38x1709762","equip_model":"WS28-2","equipment_sl_no":"WS28-2-28150","equi_desc":"WATER SPLINKER","equip_category":"S","equip_war_terms":"C&M EQPT - 3000 Hrs OR 1 Year","eq_last_hmr":"1800","eq_last_km_run":"0","functional_loc":"1304-SCCLT-MHR-RGM2","functional_loc_idofreference":"45x1642527","functional_loc_Label":"1304-SCCLT-MHR-RGM2","account_id":"SCCL RAMAGUNDAM","account_id_idofreference":"11x1632294","account_id_Label":"SCCL RAMAGUNDAM","eq_run_war_st":"Outside Warranty","equipmentid":"1709762","starred":""},{"id":"38x1707532","equip_model":"WS28-2","equipment_sl_no":"WS28-2-28044","equi_desc":"WATER SPLINKER**","equip_category":"S","equip_war_terms":"C&M EQPT - 3000 Hrs OR 1 Year","eq_last_hmr":"11441","eq_last_km_run":"0","functional_loc":"1304-SCCLT-MHR-RGM2","functional_loc_idofreference":"45x1642527","functional_loc_Label":"1304-SCCLT-MHR-RGM2","account_id":"SCCL RAMAGUNDAM","account_id_idofreference":"11x1632294","account_id_Label":"SCCL RAMAGUNDAM","eq_run_war_st":"Outside Warranty","equipmentid":"1707532","starred":""},{"id":"38x1707028","equip_model":"WS28-2","equipment_sl_no":"WS28-2-28024","equi_desc":"WATER SPRINKLER","equip_category":"S","equip_war_terms":"C&M EQPT - 3000 Hrs OR 1 Year","eq_last_hmr":"32","eq_last_km_run":"0","functional_loc":"1304-SCCLT-MHR-RGM2","functional_loc_idofreference":"45x1642527","functional_loc_Label":"1304-SCCLT-MHR-RGM2","account_id":"SCCL RAMAGUNDAM","account_id_idofreference":"11x1632294","account_id_Label":"SCCL RAMAGUNDAM","eq_run_war_st":"Outside Warranty","equipmentid":"1707028","starred":""},{"id":"38x3379300","equip_model":"BH35-2","equipment_sl_no":"BH35-2-35088","equi_desc":"REAR DUMPER","equip_category":"S","equip_war_terms":"C&M EQPT - 3000 Hrs OR 1 Year","eq_last_hmr":"8923","eq_last_km_run":"0","functional_loc":"1304-SCCLT-MHR-RGM2","functional_loc_idofreference":"45x1642527","functional_loc_Label":"1304-SCCLT-MHR-RGM2","account_id":"SCCL RAMAGUNDAM","account_id_idofreference":"11x1632294","account_id_Label":"SCCL RAMAGUNDAM","eq_run_war_st":"Outside Warranty","equipmentid":"3379300","starred":""},{"id":"38x3379272","equip_model":"BH35-2","equipment_sl_no":"BH35-2-35087","equi_desc":"REAR DUMPER","equip_category":"S","equip_war_terms":"C&M EQPT - 3000 Hrs OR 1 Year","eq_last_hmr":"7930","eq_last_km_run":"0","functional_loc":"1304-SCCLT-MHR-RGM2","functional_loc_idofreference":"45x1642527","functional_loc_Label":"1304-SCCLT-MHR-RGM2","account_id":"SCCL RAMAGUNDAM","account_id_idofreference":"11x1632294","account_id_Label":"SCCL RAMAGUNDAM","eq_run_war_st":"Outside Warranty","equipmentid":"3379272","starred":""},{"id":"38x3379136","equip_model":"BH35-2","equipment_sl_no":"BH35-2-35083","equi_desc":"REAR DUMPER*","equip_category":"S","equip_war_terms":"C&M EQPT - 3000 Hrs OR 1 Year","eq_last_hmr":"8640","eq_last_km_run":"0","functional_loc":"1304-SCCLT-MHR-RGM2","functional_loc_idofreference":"45x1642527","functional_loc_Label":"1304-SCCLT-MHR-RGM2","account_id":"SCCL RAMAGUNDAM","account_id_idofreference":"11x1632294","account_id_Label":"SCCL RAMAGUNDAM","eq_run_war_st":"Outside Warranty","equipmentid":"3379136","starred":""},{"id":"38x3379110","equip_model":"BH35-2","equipment_sl_no":"BH35-2-35082","equi_desc":"REAR DUMPER","equip_category":"S","equip_war_terms":"C&M EQPT - 3000 Hrs OR 1 Year","eq_last_hmr":"9002","eq_last_km_run":"0","functional_loc":"1304-SCCLT-MHR-RGM2","functional_loc_idofreference":"45x1642527","functional_loc_Label":"1304-SCCLT-MHR-RGM2","account_id":"SCCL RAMAGUNDAM","account_id_idofreference":"11x1632294","account_id_Label":"SCCL RAMAGUNDAM","eq_run_war_st":"Outside Warranty","equipmentid":"3379110","starred":""},{"id":"38x3378391","equip_model":"BH35-2","equipment_sl_no":"BH35-2-35050","equi_desc":"REAR DUMPER**","equip_category":"S","equip_war_terms":"C&M EQPT - 3000 Hrs OR 1 Year","eq_last_hmr":"9008","eq_last_km_run":"0","functional_loc":"1304-SCCLT-MHR-RGM2","functional_loc_idofreference":"45x1642527","functional_loc_Label":"1304-SCCLT-MHR-RGM2","account_id":"SCCL RAMAGUNDAM","account_id_idofreference":"11x1632294","account_id_Label":"SCCL RAMAGUNDAM","eq_run_war_st":"Outside Warranty","equipmentid":"3378391","starred":""},{"id":"38x3378363","equip_model":"BH35-2","equipment_sl_no":"BH35-2-35049","equi_desc":"REAR DUMPER**","equip_category":"S","equip_war_terms":"C&M EQPT - 3000 Hrs OR 1 Year","eq_last_hmr":"8652","eq_last_km_run":"0","functional_loc":"1304-SCCLT-MHR-RGM2","functional_loc_idofreference":"45x1642527","functional_loc_Label":"1304-SCCLT-MHR-RGM2","account_id":"SCCL RAMAGUNDAM","account_id_idofreference":"11x1632294","account_id_Label":"SCCL RAMAGUNDAM","eq_run_war_st":"Outside Warranty","equipmentid":"3378363","starred":""},{"id":"38x3376377","equip_model":"BH35-2","equipment_sl_no":"BH35-2-1420","equi_desc":"REAR DUMPER","equip_category":"S","equip_war_terms":"C&M EQPT - 3000 Hrs","eq_last_hmr":"2357","eq_last_km_run":"0","functional_loc":"1304-SCCLT-MHR-RGM2","functional_loc_idofreference":"45x1642527","functional_loc_Label":"1304-SCCLT-MHR-RGM2","account_id":"SCCL RAMAGUNDAM","account_id_idofreference":"11x1632294","account_id_Label":"SCCL RAMAGUNDAM","eq_run_war_st":"Under Warranty","equipmentid":"3376377","starred":""},{"id":"38x3375593","equip_model":"BH35-2","equipment_sl_no":"BH35-2-1397","equi_desc":"REAR DUMPER**","equip_category":"S","equip_war_terms":"C&M EQPT - 3000 Hrs","eq_last_hmr":"2841","eq_last_km_run":"0","functional_loc":"1304-SCCLT-MHR-RGM2","functional_loc_idofreference":"45x1642527","functional_loc_Label":"1304-SCCLT-MHR-RGM2","account_id":"SCCL RAMAGUNDAM","account_id_idofreference":"11x1632294","account_id_Label":"SCCL RAMAGUNDAM","eq_run_war_st":"Under Warranty","equipmentid":"3375593","starred":""},{"id":"38x3375559","equip_model":"BH35-2","equipment_sl_no":"BH35-2-1396","equi_desc":"REAR DUMPER**","equip_category":"S","equip_war_terms":"C&M EQPT - 3000 Hrs","eq_last_hmr":"2427","eq_last_km_run":"0","functional_loc":"1304-SCCLT-MHR-RGM2","functional_loc_idofreference":"45x1642527","functional_loc_Label":"1304-SCCLT-MHR-RGM2","account_id":"SCCL RAMAGUNDAM","account_id_idofreference":"11x1632294","account_id_Label":"SCCL RAMAGUNDAM","eq_run_war_st":"Under Warranty","equipmentid":"3375559","starred":""},{"id":"38x3375525","equip_model":"BH35-2","equipment_sl_no":"BH35-2-1395","equi_desc":"REAR DUMPER**","equip_category":"S","equip_war_terms":"C&M EQPT - 3000 Hrs","eq_last_hmr":"2906","eq_last_km_run":"0","functional_loc":"1304-SCCLT-MHR-RGM2","functional_loc_idofreference":"45x1642527","functional_loc_Label":"1304-SCCLT-MHR-RGM2","account_id":"SCCL RAMAGUNDAM","account_id_idofreference":"11x1632294","account_id_Label":"SCCL RAMAGUNDAM","eq_run_war_st":"Under Warranty","equipmentid":"3375525","starred":""},{"id":"38x3375117","equip_model":"BH35-2","equipment_sl_no":"BH35-2-1383","equi_desc":"REAR DUMPER","equip_category":"S","equip_war_terms":"C&M EQPT - 3000 Hrs","eq_last_hmr":"2369","eq_last_km_run":"0","functional_loc":"1304-SCCLT-MHR-RGM2","functional_loc_idofreference":"45x1642527","functional_loc_Label":"1304-SCCLT-MHR-RGM2","account_id":"SCCL RAMAGUNDAM","account_id_idofreference":"11x1632294","account_id_Label":"SCCL RAMAGUNDAM","eq_run_war_st":"Under Warranty","equipmentid":"3375117","starred":""},{"id":"38x3374990","equip_model":"BH35-2","equipment_sl_no":"BH35-2-1379","equi_desc":"REAR DUMPER**","equip_category":"S","equip_war_terms":"C&M EQPT - 3000 Hrs","eq_last_hmr":"3631","eq_last_km_run":"0","functional_loc":"1304-SCCLT-MHR-RGM2","functional_loc_idofreference":"45x1642527","functional_loc_Label":"1304-SCCLT-MHR-RGM2","account_id":"SCCL RAMAGUNDAM","account_id_idofreference":"11x1632294","account_id_Label":"SCCL RAMAGUNDAM","eq_run_war_st":"Outside Warranty","equipmentid":"3374990","starred":""},{"id":"38x3374675","equip_model":"BH35-2","equipment_sl_no":"BH35-2-1370","equi_desc":"REAR DUMPER**","equip_category":"S","equip_war_terms":"C&M EQPT - 3000 Hrs","eq_last_hmr":"876","eq_last_km_run":"0","functional_loc":"1304-SCCLT-MHR-RGM2","functional_loc_idofreference":"45x1642527","functional_loc_Label":"1304-SCCLT-MHR-RGM2","account_id":"SCCL RAMAGUNDAM","account_id_idofreference":"11x1632294","account_id_Label":"SCCL RAMAGUNDAM","eq_run_war_st":"Under Warranty","equipmentid":"3374675","starred":""},{"id":"38x3374389","equip_model":"BH35-2","equipment_sl_no":"BH35-2-1362","equi_desc":"REAR DUMPER**","equip_category":"S","equip_war_terms":"C&M EQPT - 3000 Hrs","eq_last_hmr":"2625","eq_last_km_run":"0","functional_loc":"1304-SCCLT-MHR-RGM2","functional_loc_idofreference":"45x1642527","functional_loc_Label":"1304-SCCLT-MHR-RGM2","account_id":"SCCL RAMAGUNDAM","account_id_idofreference":"11x1632294","account_id_Label":"SCCL RAMAGUNDAM","eq_run_war_st":"Under Warranty","equipmentid":"3374389","starred":""},{"id":"38x3370419","equip_model":"BH35-2","equipment_sl_no":"BH35-2-1221","equi_desc":"BH35-2 DUMPER","equip_category":"S","equip_war_terms":"C&M EQPT - 3000 Hrs OR 1 Year","eq_last_hmr":"7850","eq_last_km_run":"0","functional_loc":"1304-SCCLT-MHR-RGM2","functional_loc_idofreference":"45x1642527","functional_loc_Label":"1304-SCCLT-MHR-RGM2","account_id":"SCCL RAMAGUNDAM","account_id_idofreference":"11x1632294","account_id_Label":"SCCL RAMAGUNDAM","eq_run_war_st":"Outside Warranty","equipmentid":"3370419","starred":""},{"id":"38x3370392","equip_model":"BH35-2","equipment_sl_no":"BH35-2-1220","equi_desc":"BH35-2 DUMPER","equip_category":"S","equip_war_terms":"C&M EQPT - 3000 Hrs OR 1 Year","eq_last_hmr":"5971","eq_last_km_run":"0","functional_loc":"1304-SCCLT-MHR-RGM2","functional_loc_idofreference":"45x1642527","functional_loc_Label":"1304-SCCLT-MHR-RGM2","account_id":"SCCL RAMAGUNDAM","account_id_idofreference":"11x1632294","account_id_Label":"SCCL RAMAGUNDAM","eq_run_war_st":"Outside Warranty","equipmentid":"3370392","starred":""},{"id":"38x3370364","equip_model":"BH35-2","equipment_sl_no":"BH35-2-1219","equi_desc":"BH35-2 DUMPER","equip_category":"S","equip_war_terms":"C&M EQPT - 1 Year Std Warranty","eq_last_hmr":"5706","eq_last_km_run":"0","functional_loc":"1304-SCCLT-MHR-RGM2","functional_loc_idofreference":"45x1642527","functional_loc_Label":"1304-SCCLT-MHR-RGM2","account_id":"SCCL RAMAGUNDAM","account_id_idofreference":"11x1632294","account_id_Label":"SCCL RAMAGUNDAM","eq_run_war_st":"Outside Warranty","equipmentid":"3370364","starred":""},{"id":"38x3370230","equip_model":"BH35-2","equipment_sl_no":"BH35-2-1214","equi_desc":"BH35-2 DUMPER","equip_category":"S","equip_war_terms":"C&M EQPT - 3000 Hrs OR 1 Year","eq_last_hmr":"5720","eq_last_km_run":"0","functional_loc":"1304-SCCLT-MHR-RGM2","functional_loc_idofreference":"45x1642527","functional_loc_Label":"1304-SCCLT-MHR-RGM2","account_id":"SCCL RAMAGUNDAM","account_id_idofreference":"11x1632294","account_id_Label":"SCCL RAMAGUNDAM","eq_run_war_st":"Outside Warranty","equipmentid":"3370230","starred":""},{"id":"38x3370203","equip_model":"BH35-2","equipment_sl_no":"BH35-2-1213","equi_desc":"BH35-2 DUMPER","equip_category":"S","equip_war_terms":"C&M EQPT - 3000 Hrs OR 1 Year","eq_last_hmr":"4997","eq_last_km_run":"0","functional_loc":"1304-SCCLT-MHR-RGM2","functional_loc_idofreference":"45x1642527","functional_loc_Label":"1304-SCCLT-MHR-RGM2","account_id":"SCCL RAMAGUNDAM","account_id_idofreference":"11x1632294","account_id_Label":"SCCL RAMAGUNDAM","eq_run_war_st":"Outside Warranty","equipmentid":"3370203","starred":""},{"id":"38x1873888","equip_model":"BH35","equipment_sl_no":"BH35-10147","equi_desc":"BH35-DUMPER","equip_category":"S","equip_war_terms":"C&M EQPT - 3000 Hrs OR 1 Year","eq_last_hmr":"1005","eq_last_km_run":"0","functional_loc":"1304-SCCLT-MHR-RGM2","functional_loc_idofreference":"45x1642527","functional_loc_Label":"1304-SCCLT-MHR-RGM2","account_id":"SCCL RAMAGUNDAM","account_id_idofreference":"11x1632294","account_id_Label":"SCCL RAMAGUNDAM","eq_run_war_st":"Outside Warranty","equipmentid":"1873888","starred":""},{"id":"38x1873844","equip_model":"BH35","equipment_sl_no":"BH35-10127","equi_desc":"BH35-DUMPER","equip_category":"S","equip_war_terms":"C&M EQPT - 3000 Hrs OR 1 Year","eq_last_hmr":"4562","eq_last_km_run":"0","functional_loc":"1304-SCCLT-MHR-RGM2","functional_loc_idofreference":"45x1642527","functional_loc_Label":"1304-SCCLT-MHR-RGM2","account_id":"SCCL RAMAGUNDAM","account_id_idofreference":"11x1632294","account_id_Label":"SCCL RAMAGUNDAM","eq_run_war_st":"Outside Warranty","equipmentid":"1873844","starred":""},{"id":"38x1873841","equip_model":"BH35","equipment_sl_no":"BH35-10126","equi_desc":"BH35-DUMPER","equip_category":"S","equip_war_terms":"C&M EQPT - 3000 Hrs OR 1 Year","eq_last_hmr":"4327","eq_last_km_run":"0","functional_loc":"1304-SCCLT-MHR-RGM2","functional_loc_idofreference":"45x1642527","functional_loc_Label":"1304-SCCLT-MHR-RGM2","account_id":"SCCL RAMAGUNDAM","account_id_idofreference":"11x1632294","account_id_Label":"SCCL RAMAGUNDAM","eq_run_war_st":"Outside Warranty","equipmentid":"1873841","starred":""},{"id":"38x1856093","equip_model":"BH100","equipment_sl_no":"BH100-1092","equi_desc":"BEML-BH100-REAR DUMPER","equip_category":"S","equip_war_terms":"C&M EQPT - 3000 Hrs OR 1 Year","eq_last_hmr":"6141","eq_last_km_run":"0","functional_loc":"1304-SCCLT-MHR-RGM2","functional_loc_idofreference":"45x1642527","functional_loc_Label":"1304-SCCLT-MHR-RGM2","account_id":"SCCL RAMAGUNDAM","account_id_idofreference":"11x1632294","account_id_Label":"SCCL RAMAGUNDAM","eq_run_war_st":"Outside Warranty","equipmentid":"1856093","starred":""},{"id":"38x1856019","equip_model":"BH100","equipment_sl_no":"BH100-1090","equi_desc":"BEML-BH100-REAR DUMPER","equip_category":"S","equip_war_terms":"C&M EQPT - 3000 Hrs OR 1 Year","eq_last_hmr":"9442","eq_last_km_run":"0","functional_loc":"1304-SCCLT-MHR-RGM2","functional_loc_idofreference":"45x1642527","functional_loc_Label":"1304-SCCLT-MHR-RGM2","account_id":"SCCL RAMAGUNDAM","account_id_idofreference":"11x1632294","account_id_Label":"SCCL RAMAGUNDAM","eq_run_war_st":"Outside Warranty","equipmentid":"1856019","starred":""},{"id":"38x1832310","equip_model":"BG605","equipment_sl_no":"BG605-6631","equi_desc":"MOTOR GRADER**","equip_category":"S","equip_war_terms":"C&M EQPT - 3000 Hrs OR 1 Year","eq_last_hmr":"1021","eq_last_km_run":"0","functional_loc":"1304-SCCLT-MHR-RGM2","functional_loc_idofreference":"45x1642527","functional_loc_Label":"1304-SCCLT-MHR-RGM2","account_id":"SCCL RAMAGUNDAM","account_id_idofreference":"11x1632294","account_id_Label":"SCCL RAMAGUNDAM","eq_run_war_st":"Outside Warranty","equipmentid":"1832310","starred":""},{"id":"38x1829149","equip_model":"BG605","equipment_sl_no":"BG605-6518","equi_desc":"BG605 MOTOR GRADER","equip_category":"S","equip_war_terms":"C&M EQPT - 3000 Hrs OR 1 Year","eq_last_hmr":"2135","eq_last_km_run":"0","functional_loc":"1304-SCCLT-MHR-RGM2","functional_loc_idofreference":"45x1642527","functional_loc_Label":"1304-SCCLT-MHR-RGM2","account_id":"SCCL RAMAGUNDAM","account_id_idofreference":"11x1632294","account_id_Label":"SCCL RAMAGUNDAM","eq_run_war_st":"Outside Warranty","equipmentid":"1829149","starred":""},{"id":"38x1829150","equip_model":"BG605","equipment_sl_no":"BG605-6519","equi_desc":"MOTOR GRADER","equip_category":"S","equip_war_terms":"C&M EQPT - 3000 Hrs OR 1 Year","eq_last_hmr":"1250","eq_last_km_run":"0","functional_loc":"1304-SCCLT-MHR-RGM2","functional_loc_idofreference":"45x1642527","functional_loc_Label":"1304-SCCLT-MHR-RGM2","account_id":"SCCL RAMAGUNDAM","account_id_idofreference":"11x1632294","account_id_Label":"SCCL RAMAGUNDAM","eq_run_war_st":"Outside Warranty","equipmentid":"1829150","starred":""},{"id":"38x1729948","equip_model":"BD155","equipment_sl_no":"BD155-13243","equi_desc":"BD155 DOZER","equip_category":"S","equip_war_terms":"C&M EQPT - 3000 Hrs","eq_last_hmr":"5375","eq_last_km_run":"0","functional_loc":"1304-SCCLT-MHR-RGM2","functional_loc_idofreference":"45x1642527","functional_loc_Label":"1304-SCCLT-MHR-RGM2","account_id":"SCCL, SRIRAMPUR","account_id_idofreference":"11x1634658","account_id_Label":"SCCL, SRIRAMPUR","eq_run_war_st":"Outside Warranty","equipmentid":"1729948","starred":""},{"id":"38x1727947","equip_model":"BD155","equipment_sl_no":"BD155-12881","equi_desc":"BD155 DOZER","equip_category":"S","equip_war_terms":"C&M EQPT - 12 MONTHS OR 3000 HRS","eq_last_hmr":"2785","eq_last_km_run":"0","functional_loc":"1304-SCCLT-MHR-RGM2","functional_loc_idofreference":"45x1642527","functional_loc_Label":"1304-SCCLT-MHR-RGM2","account_id":"SCCL RAMAGUNDAM","account_id_idofreference":"11x1632294","account_id_Label":"SCCL RAMAGUNDAM","eq_run_war_st":"Outside Warranty","equipmentid":"1727947","starred":""},{"id":"38x1726926","equip_model":"BD155","equipment_sl_no":"BD155-12658","equi_desc":"BD155 DOZER","equip_category":"S","equip_war_terms":"C&M EQPT - 12 MONTHS OR 3000 HRS","eq_last_hmr":"3576","eq_last_km_run":"0","functional_loc":"1304-SCCLT-MHR-RGM2","functional_loc_idofreference":"45x1642527","functional_loc_Label":"1304-SCCLT-MHR-RGM2","account_id":"SCCL RAMAGUNDAM","account_id_idofreference":"11x1632294","account_id_Label":"SCCL RAMAGUNDAM","eq_run_war_st":"Outside Warranty","equipmentid":"1726926","starred":""},{"id":"38x1726920","equip_model":"BD155","equipment_sl_no":"BD155-12657","equi_desc":"BD155 DOZER","equip_category":"S","equip_war_terms":"C&M EQPT - 12 MONTHS OR 3000 HRS","eq_last_hmr":"10735","eq_last_km_run":"0","functional_loc":"1304-SCCLT-MHR-RGM2","functional_loc_idofreference":"45x1642527","functional_loc_Label":"1304-SCCLT-MHR-RGM2","account_id":"SCCL RAMAGUNDAM","account_id_idofreference":"11x1632294","account_id_Label":"SCCL RAMAGUNDAM","eq_run_war_st":"Outside Warranty","equipmentid":"1726920","starred":""}]